{
  "project_info": {
    "project_number": "90938323172",
    "firebase_url": "https://what4lunch-363e5.firebaseio.com",
    "project_id": "what4lunch-363e5",
    "storage_bucket": "what4lunch-363e5.appspot.com"
  },
  "client": [
    {
      "client_info": {
        "mobilesdk_app_id": "1:90938323172:android:893216cc43dd499052bcf1",
        "android_client_info": {
          "package_name": "com.dongy.w4l"
        }
      },
      "oauth_client": [
        {
          "client_id": "90938323172-u3hdjkn2hu11mgtbji4nr11kre8b54fd.apps.googleusercontent.com",
          "client_type": 3
        }
      ],
      "api_key": [
        {
          "current_key": "AIzaSyBxXL4rCEKCkD8t_p9lI-LHmmVX8oMokzg"
        }
      ],
      "services": {
        "appinvite_service": {
          "other_platform_oauth_client": [
            {
              "client_id": "90938323172-u3hdjkn2hu11mgtbji4nr11kre8b54fd.apps.googleusercontent.com",
              "client_type": 3
            }
          ]
        }
      }
    }
  ],
  "configuration_version": "1"
}